{"cores": [{"repository_name": "ibex", "repository_url": "https://github.com/lowRISC/ibex", "repository_branch": "master", "repository_revision": "bac72d96ec713a68ed07f3e1cb341ffbf40b8228"}, {"repository_name": "Cores-VeeR-EL2", "repository_url": "https://github.com/chipsalliance/Cores-VeeR-EL2", "repository_branch": "main", "repository_revision": "61739fedd0ac62e2345a454cda064d612d4d457a"}, {"repository_name": "caliptra-rtl", "repository_url": "https://github.com/chipsalliance/caliptra-rtl", "repository_branch": "main", "repository_revision": "020d3155f57155d6a25aebc3a121a361e4801047"}]}