{"cores": [{"repository_name": "ibex", "repository_url": "https://github.com/lowRISC/ibex", "repository_branch": "master", "repository_revision": "1449ed5ea8f3d03127f7c3624e635e132830367d"}, {"repository_name": "Cores-VeeR-EL2", "repository_url": "https://github.com/chipsalliance/Cores-VeeR-EL2", "repository_branch": "main", "repository_revision": "27899fb8d565669da3cb32daccf1f01abcae2d16"}, {"repository_name": "caliptra-rtl", "repository_url": "https://github.com/chipsalliance/caliptra-rtl", "repository_branch": "main", "repository_revision": "41b77ba0a885fdeaa548e6f80030d6797c76a5f8"}]}