{"cores": [{"repository_name": "ibex", "repository_url": "https://github.com/lowRISC/ibex", "repository_branch": "master", "repository_revision": "c1139477dc15d9b2f8d689715e2c59f7a689f693"}, {"repository_name": "Cores-VeeR-EL2", "repository_url": "https://github.com/chipsalliance/Cores-VeeR-EL2", "repository_branch": "main", "repository_revision": "d6fe0beba3f76e24500a22bda43ef2306e76503f"}, {"repository_name": "caliptra-rtl", "repository_url": "https://github.com/chipsalliance/caliptra-rtl", "repository_branch": "main", "repository_revision": "778da6f41dc046f883a2b5ab4b1ee19df2fc4d8f"}]}